django_migrations_diff/__init__.py
django_migrations_diff/__main__.py
django_migrations_diff/help_text.py
django_migrations_diff/main.py
django_migrations_diff-2.0.5.dist-info/LICENSE
django_migrations_diff-2.0.5.dist-info/METADATA
django_migrations_diff-2.0.5.dist-info/WHEEL
django_migrations_diff-2.0.5.dist-info/entry_points.txt
django_migrations_diff-2.0.5.dist-info/top_level.txt
django_migrations_diff-2.0.5.dist-info/RECORD
