Metadata-Version: 2.1
Name: django-migrations-diff
Version: 2.0.5
Summary: CLI for comparing Django migrations between two snapshots.
Home-page: https://github.com/deniskrumko/django-migrations-diff
Author: Denis Krumko
Author-email: dkrumko@gmail.com
License: MIT
Keywords: CLI,Django,Migrations,Diff
Platform: UNKNOWN
Classifier: Development Status :: 4 - Beta
Classifier: Intended Audience :: Developers
Classifier: Natural Language :: English
Classifier: Environment :: Console
Classifier: License :: OSI Approved :: MIT License
Classifier: Programming Language :: Python
Classifier: Programming Language :: Python :: 3
Classifier: Programming Language :: Python :: 3.6
Classifier: Programming Language :: Python :: 3.7
Classifier: Programming Language :: Python :: 3.8
Classifier: Programming Language :: Python :: Implementation :: CPython
Classifier: Topic :: Software Development :: Libraries
Classifier: Topic :: Utilities
Requires-Python: >=3.6
Requires-Dist: requests
